pprl_model/__init__.py
pprl_model/common.py
pprl_model/mask.py
pprl_model/match.py
pprl_model/transform.py
pprl_model-0.1.6.dist-info/LICENSE
pprl_model-0.1.6.dist-info/METADATA
pprl_model-0.1.6.dist-info/WHEEL
pprl_model-0.1.6.dist-info/RECORD
