Metadata-Version: 2.3
Name: pprl-model
Version: 0.1.6
Summary: Data models for use with a HTTP-based service for privacy-preserving record linkage using Bloom filters.
License: MIT
Keywords: record linkage,privacy,bloom filter
Author: Maximilian Jugl
Author-email: Maximilian.Jugl@medizin.uni-leipzig.de
Requires-Python: >=3.10
Classifier: Development Status :: 4 - Beta
Classifier: Intended Audience :: Developers
Classifier: Intended Audience :: Science/Research
Classifier: Topic :: Software Development :: Libraries :: Python Modules
Requires-Dist: pydantic (>=2.7.0,<3.0.0)
Project-URL: Repository, https://github.com/ul-mds/pprl
